{
  "kik_id": "kik_81c20b22ab163c78844b",
  "slug": "2014-uh-ii-3484-3c78844b",
  "search_key": "2014UHII3484",
  "decision_label": "2014-UH.II-3484",
  "filename": "2014.10.22_KIK_2014-UH.II-3484.pdf",
  "court_decision_count": 1,
  "court_decisions": [
    {
      "relationship_id": "rel_1efde706429a9120bdb9",
      "court_id": "court_026195423bf31483e389",
      "court_slug": "2015-03-04-idare-2015-mk-92-1483e389",
      "court_filename": "2015.03.04_IDARE_2015_MK-92.pdf",
      "match_type": "exact_filename_key",
      "match_status": "EXACT_FILENAME_KEY_MATCH",
      "confidence": 100
    }
  ]
}