{
  "kik_id": "kik_331d73fbaf424d4ce3e7",
  "slug": "2017-uh-ii-3190-4d4ce3e7",
  "search_key": "2017UHII3190",
  "decision_label": "2017-UH.II-3190",
  "filename": "2017.11.30_KIK_2017-UH.II-3190.pdf",
  "court_decision_count": 1,
  "court_decisions": [
    {
      "relationship_id": "rel_a97a84f6e11e3a7e3143",
      "court_id": "court_f82d4ef77c8b9a8ee23e",
      "court_slug": "2018-02-27-idare-2018-mk-70-9a8ee23e",
      "court_filename": "2018.02.27_IDARE_2018_MK-70.pdf",
      "match_type": "exact_filename_key",
      "match_status": "EXACT_FILENAME_KEY_MATCH",
      "confidence": 100
    }
  ]
}