{
  "kik_id": "kik_192d2bf5d9236f849e17",
  "slug": "2021-uh-i-1031-6f849e17",
  "search_key": "2021UHI1031",
  "decision_label": "2021-UH.I-1031",
  "filename": "2021.05.20_KIK_2021-UH.I-1031.pdf",
  "court_decision_count": 1,
  "court_decisions": [
    {
      "relationship_id": "rel_8fdaf61addcc0f187dc7",
      "court_id": "court_af356cded4850dcc017b",
      "court_slug": "2021-08-25-idare-2021-mk-384-0dcc017b",
      "court_filename": "2021.08.25_IDARE_2021_MK-384.pdf",
      "match_type": "exact_filename_key",
      "match_status": "EXACT_FILENAME_KEY_MATCH",
      "confidence": 100
    }
  ]
}